Metadata-Version: 2.1
Name: fontain
Version: 0.1.1
Summary: Python tool for font recognition on images
Home-page: https://github.com/baton96/fontain
Author: Bartosz Paulewicz
Author-email: podolce0@gmail.com
License: MIT
Download-URL: https://github.com/baton96/fontain/archive/refs/tags/0.1.1.tar.gz
Keywords: font,ocr
Platform: UNKNOWN
Classifier: Development Status :: 3 - Alpha
Classifier: Intended Audience :: Developers
Classifier: Topic :: Software Development :: Build Tools
Classifier: License :: OSI Approved :: MIT License
Classifier: Programming Language :: Python :: 3
License-File: LICENSE.txt
